llmgine/__init__.py
llmgine/bootstrap.py
llmgine/py.typed
llmgine/bus/README.md
llmgine/bus/__init__.py
llmgine/bus/backpressure.py
llmgine/bus/bus.py
llmgine/bus/filters.py
llmgine/bus/interfaces.py
llmgine/bus/metrics.py
llmgine/bus/middleware.py
llmgine/bus/registry.py
llmgine/bus/resilience.py
llmgine/bus/session.py
llmgine/bus/utils.py
llmgine/database/__init__.py
llmgine/database/database.py
llmgine/llm/__init__.py
llmgine/llm/context/__init__.py
llmgine/llm/context/memory.py
llmgine/llm/tools/README.md
llmgine/llm/tools/__init__.py
llmgine/llm/tools/exceptions.py
llmgine/llm/tools/llmgine_mcp_server.py
llmgine/llm/tools/simple_tools.py
llmgine/llm/tools/tool.py
llmgine/llm/tools/toolCall.py
llmgine/llm/tools/tool_events.py
llmgine/llm/tools/tool_manager.py
llmgine/llm/tools/tool_parser.py
llmgine/llm/tools/tool_register.py
llmgine/llm/tools/validation.py
llmgine/llm/tools/mcp/__init__.py
llmgine/llm/tools/mcp/mcp_servers.py
llmgine/llm/tools/mcp/mcp_tool_adapter.py
llmgine/llm/tools/mcp/mcp_tool_manager.py
llmgine/messages/__init__.py
llmgine/messages/approvals.py
llmgine/messages/commands.py
llmgine/messages/events.py
llmgine/messages/scheduled_events.py
llmgine/observability/README.md
llmgine/observability/__init__.py
llmgine/observability/events.py
llmgine/observability/manager.py
llmgine/observability/otel_handler.py
llmgine/observability/handlers/__init__.py
llmgine/observability/handlers/adapters.py
llmgine/observability/handlers/base.py
llmgine/observability/handlers/base_sync.py
llmgine/observability/handlers/console.py
llmgine/observability/handlers/console_sync.py
llmgine/observability/handlers/file.py
llmgine/observability/handlers/file_sync.py
llmgine/ui/__init__.py
llmgine/ui/app.py
llmgine/ui/handlers_catalog.py
llmgine/ui/hub.py
llmgine/ui/loadgen.py
llmgine/ui/observability_ui.py
llmgine/ui/state.py
llmgine/ui/cli/__init__.py
llmgine/ui/cli/cli.py
llmgine/ui/cli/components.py
llmgine/ui/cli/config.py
llmgine/ui/static/main.js
llmgine-0.0.1.dist-info/METADATA
llmgine-0.0.1.dist-info/WHEEL
llmgine-0.0.1.dist-info/licenses/LICENSE
llmgine-0.0.1.dist-info/RECORD
