Metadata-Version: 2.4
Name: llmgine
Version: 0.0.1
Summary: An application framework for building LLM-powered applications.
Project-URL: Homepage, https://nathan-luo.github.io/llmgine/
Project-URL: Repository, https://github.com/nathan-luo/llmgine
Project-URL: Documentation, https://nathan-luo.github.io/llmgine/
Author-email: Nathan Luo <nathanluo13@gmail.com>
License-File: LICENSE
Keywords: python
Classifier: Intended Audience :: Developers
Classifier: Programming Language :: Python
Classifier: Programming Language :: Python :: 3
Classifier: Programming Language :: Python :: 3.11
Classifier: Programming Language :: Python :: 3.12
Classifier: Programming Language :: Python :: 3.13
Classifier: Topic :: Software Development :: Libraries :: Python Modules
Requires-Python: <4.0,>=3.11
Requires-Dist: aiofiles>=24.1.0
Requires-Dist: aiosqlite>=0.21.0
Requires-Dist: discord>=2.3.2
Requires-Dist: dotenv>=0.9.9
Requires-Dist: fastapi>=0.117.1
Requires-Dist: icecream>=2.1.4
Requires-Dist: instructor>=1.7.9
Requires-Dist: ipdb>=0.13.13
Requires-Dist: ipython>=8.18.1
Requires-Dist: jinja2>=3.1.6
Requires-Dist: litellm>=1.63.12
Requires-Dist: load-dotenv>=0.1.0
Requires-Dist: mcp>=1.10.1
Requires-Dist: notion-client>=2.3.0
Requires-Dist: pandas>=2.2.3
Requires-Dist: prompt-toolkit>=3.0.51
Requires-Dist: psutil>=7.0.0
Requires-Dist: psycopg2-binary>=2.9.10
Requires-Dist: pydantic>=2.11.3
Requires-Dist: pyreadline>=2.1
Requires-Dist: pytest-asyncio>=0.25.3
Requires-Dist: pytest>=8.3.5
Requires-Dist: python-dotenv>=1.1.0
Requires-Dist: rich>=13.9.4
Requires-Dist: sqlalchemy>=2.0.40
Requires-Dist: textual>=2.1.2
Requires-Dist: uvicorn>=0.35.0
Requires-Dist: websockets>=15.0.1
Provides-Extra: opentelemetry
Requires-Dist: opentelemetry-api>=1.20.0; extra == 'opentelemetry'
Requires-Dist: opentelemetry-exporter-otlp>=1.20.0; extra == 'opentelemetry'
Requires-Dist: opentelemetry-sdk>=1.20.0; extra == 'opentelemetry'
Requires-Dist: opentelemetry-semantic-conventions>=0.41b0; extra == 'opentelemetry'
